lollmsvectordb/__init__.py
lollmsvectordb/directory_binding.py
lollmsvectordb/llm_model.py
lollmsvectordb/remote_rag_database.py
lollmsvectordb/text_chunker.py
lollmsvectordb/text_document_loader.py
lollmsvectordb/tokenizer.py
lollmsvectordb/vector_database.py
lollmsvectordb/vectorizer.py
lollmsvectordb/algorithms/__init__.py
lollmsvectordb/algorithms/kneighbors.py
lollmsvectordb/database_clients/__init__.py
lollmsvectordb/database_clients/lightrag_client.py
lollmsvectordb/database_elements/__init__.py
lollmsvectordb/database_elements/chunk.py
lollmsvectordb/database_elements/document.py
lollmsvectordb/lollms_tokenizers/__init__.py
lollmsvectordb/lollms_tokenizers/tiktoken_tokenizer.py
lollmsvectordb/lollms_vectorizers/__init__.py
lollmsvectordb/lollms_vectorizers/graphrag_vectorizer.py
lollmsvectordb/lollms_vectorizers/lightrag_vectorizer.py
lollmsvectordb/lollms_vectorizers/ollama_vectorizer.py
lollmsvectordb/lollms_vectorizers/openai_vectorizer.py
lollmsvectordb/lollms_vectorizers/semantic_vectorizer.py
lollmsvectordb/lollms_vectorizers/tfidf_vectorizer.py
lollmsvectordb-1.3.8.dist-info/LICENSE
lollmsvectordb-1.3.8.dist-info/METADATA
lollmsvectordb-1.3.8.dist-info/WHEEL
lollmsvectordb-1.3.8.dist-info/top_level.txt
lollmsvectordb-1.3.8.dist-info/RECORD
