Metadata-Version: 2.1
Name: lollmsvectordb
Version: 1.3.8
Summary: A modular text-based database manager for retrieval-augmented generation (RAG), seamlessly integrating with the LoLLMs ecosystem.
Home-page: https://github.com/ParisNeo/LoLLMsVectorDB
Author: ParisNeo
Author-email: parisneoai@gmail.com
Classifier: Programming Language :: Python :: 3
Classifier: License :: OSI Approved :: MIT License
Classifier: Operating System :: OS Independent
Requires-Python: >=3.6
License-File: LICENSE
Requires-Dist: numpy ==1.26.3
Requires-Dist: tiktoken
Requires-Dist: ascii-colors
Requires-Dist: tqdm
Requires-Dist: transformers
Requires-Dist: torch
Requires-Dist: docling
Requires-Dist: PyPDF2
Requires-Dist: openai
Requires-Dist: dpkt
Requires-Dist: pipmaster
Requires-Dist: python-docx
Requires-Dist: pandas
Requires-Dist: openpyxl
Requires-Dist: beautifulsoup4
Requires-Dist: extract-msg
